azure/purview/datamap/__init__.py
azure/purview/datamap/_client.py
azure/purview/datamap/_configuration.py
azure/purview/datamap/_model_base.py
azure/purview/datamap/_patch.py
azure/purview/datamap/_serialization.py
azure/purview/datamap/_vendor.py
azure/purview/datamap/_version.py
azure/purview/datamap/py.typed
azure/purview/datamap/aio/__init__.py
azure/purview/datamap/aio/_client.py
azure/purview/datamap/aio/_configuration.py
azure/purview/datamap/aio/_patch.py
azure/purview/datamap/aio/operations/__init__.py
azure/purview/datamap/aio/operations/_operations.py
azure/purview/datamap/aio/operations/_patch.py
azure/purview/datamap/models/__init__.py
azure/purview/datamap/models/_enums.py
azure/purview/datamap/models/_models.py
azure/purview/datamap/models/_patch.py
azure/purview/datamap/operations/__init__.py
azure/purview/datamap/operations/_operations.py
azure/purview/datamap/operations/_patch.py
azure_purview_datamap-1.0.0b2.dist-info/LICENSE
azure_purview_datamap-1.0.0b2.dist-info/METADATA
azure_purview_datamap-1.0.0b2.dist-info/WHEEL
azure_purview_datamap-1.0.0b2.dist-info/top_level.txt
azure_purview_datamap-1.0.0b2.dist-info/RECORD
